tests/__init__.py
tests/test_scheduler.py
zeppos_airflow/__init__.py
zeppos_airflow/scheduler.py
zeppos_airflow-0.0.6.dist-info/LICENSE
zeppos_airflow-0.0.6.dist-info/METADATA
zeppos_airflow-0.0.6.dist-info/WHEEL
zeppos_airflow-0.0.6.dist-info/top_level.txt
zeppos_airflow-0.0.6.dist-info/RECORD
